arknet/__init__.py
arknet/__main__.py
arknet/core.py
arknet/py.typed
arknet-0.1.0.dist-info/METADATA
arknet-0.1.0.dist-info/WHEEL
arknet-0.1.0.dist-info/entry_points.txt
arknet-0.1.0.dist-info/licenses/LICENSE
arknet-0.1.0.dist-info/RECORD
